{
  "applications": "*",
  "changelogDate": "20231114152808",
  "entityTableName": "solicitud",
  "fields": [
    {
      "fieldName": "codigo",
      "fieldType": "UUID"
    },
    {
      "fieldName": "descripcion",
      "fieldType": "String"
    }
  ],
  "name": "Solicitud",
  "relationships": [
    {
      "otherEntityName": "user",
      "relationshipName": "usuario",
      "relationshipSide": "left",
      "relationshipType": "one-to-one",
      "relationshipWithBuiltInEntity": true
    },
    {
      "otherEntityName": "servicio",
      "otherEntityRelationshipName": "solicitud",
      "relationshipName": "servicio",
      "relationshipSide": "right",
      "relationshipType": "one-to-one"
    }
  ],
  "searchEngine": "no"
}
